{"headings":["giriş","genel","matematik-kipiyle-metin-kipi-arasındaki-farklar","gruplandırma","boşluklar","parantezler-gruplandırıcılar-ve-oklar","yunan-harfleri","fonksiyonlar","yığın-simgeleri","matrisler","yazı-biçem-ve-boyutları","denklem-ortamları","teorem-ve-benzeri-ortamlar","temel-teoremler","sayaçlar","kanıtlar","teorem-stilleri","özel-stiller"],"options":{"chapters":true},"entries":[{"order":{"number":1,"section":[4,2,0,0,0,0,0]},"caption":"Gruplandırıcılar","key":"tbl-grup"},{"order":{"number":4,"section":[4,7,0,0,0,0,0]},"caption":"Matematik Kipinde Yazı Biçemleri","key":"tbl-matyazi"},{"order":{"number":3,"section":[4,3,0,0,0,0,0]},"caption":"Yunan Harfleri","key":"tbl-yunan"},{"order":{"number":5,"section":[4,9,4,0,0,0,0]},"caption":"Teorem Stilleri","key":"tbl-teoremstil"},{"order":{"number":2,"section":[4,2,0,0,0,0,0]},"caption":"Oklar","key":"tbl-oklar"}]}